{
    "/assets/js/group-page.js": "/assets/js/group-page.js",
    "/assets/js/group-page.js.map": "/assets/js/group-page.js.map",
    "/assets/js/myaccount-page.js": "/assets/js/myaccount-page.js",
    "/assets/js/myaccount-page.js.map": "/assets/js/myaccount-page.js.map",
    "/assets/js/register-page.js": "/assets/js/register-page.js",
    "/assets/js/register-page.js.map": "/assets/js/register-page.js.map",
    "/assets/js/user-page.js": "/assets/js/user-page.js",
    "/assets/js/user-page.js.map": "/assets/js/user-page.js.map"
}
